<?xml version="1.0" encoding="utf-8"?>
<!--Ginger Repository Item created with version: 2.7.0.0-->
<Ginger.Run.RunSetConfig Created="2/20/2018 6:17:05 PM" CreatedBy="AVDHOOTN" Guid="e76d5e04-dd96-4caf-b48f-d7b6cc041539" LastUpdate="9/5/2018 7:50:30 AM" LastUpdateBy="AVDHOOTN" Name="BAUSTTOOL" ParentGuid="00000000-0000-0000-0000-000000000000" RunModeParallel="True" RunWithAnalyzer="True" Version="23">
<GingerRunners>
<Ginger.Run.GingerRunner Active="True" Created="3/8/2018 11:52:37 AM" CreatedBy="AVDHOOTN" FilterExecutionByTags="False" Guid="66d6e965-19c9-48d0-972e-4cc240f976e0" LastUpdate="1/1/0001 12:00:00 AM" Name="Runner 0" ParentGuid="00000000-0000-0000-0000-000000000000" RunOption="ContinueToRunall" Selected="False" UseSpecificEnvironment="False" Version="0">
<ApplicationAgents>
<GingerCore.Platforms.ApplicationAgent AgentName="JavaDriver" AppName="MyJavaApp" Created="9/5/2018 7:50:28 AM" CreatedBy="AVDHOOTN" Guid="218d4c73-6b53-4f75-b0b3-f0f452855b2d" LastUpdate="1/1/0001 12:00:00 AM" ParentGuid="00000000-0000-0000-0000-000000000000" Version="0" />
<GingerCore.Platforms.ApplicationAgent AgentName="ASCF" AppName="CRM" Created="9/5/2018 7:50:28 AM" CreatedBy="AVDHOOTN" Guid="8fd3d8f6-700b-49b2-9c4f-f0e4f9508727" LastUpdate="1/1/0001 12:00:00 AM" ParentGuid="00000000-0000-0000-0000-000000000000" Version="0" />
<GingerCore.Platforms.ApplicationAgent AgentName="IE" AppName="IE" Created="9/5/2018 7:50:28 AM" CreatedBy="AVDHOOTN" Guid="7cd50a6e-00d3-4b6f-bd6c-68392e3f878b" LastUpdate="1/1/0001 12:00:00 AM" ParentGuid="00000000-0000-0000-0000-000000000000" Version="0" />
</ApplicationAgents>

<BusinessFlowsRunList>
<Ginger.Run.BusinessFlowRun BusinessFlowGuid="8c0c3d3a-dd20-47bb-a1d4-c84992fce803" BusinessFlowInstanceGuid="98d67ec2-0458-406e-b486-d6944f312e99" BusinessFlowIsActive="True" BusinessFlowIsMandatory="False" BusinessFlowName="BAU Smoke Test" Created="9/5/2018 7:50:30 AM" CreatedBy="AVDHOOTN" Guid="7a3d9403-420f-4a0e-84d6-bd8341fe9e00" LastUpdate="1/1/0001 12:00:00 AM" ParentGuid="00000000-0000-0000-0000-000000000000" Version="0">
<BFFlowControls>
</BFFlowControls>

<BusinessFlowCustomizedRunVariables>
</BusinessFlowCustomizedRunVariables>
</Ginger.Run.BusinessFlowRun>
</BusinessFlowsRunList>

<FilterExecutionTags>
</FilterExecutionTags>
</Ginger.Run.GingerRunner>
</GingerRunners>

<RunSetActions>
</RunSetActions>

<Tags>
</Tags>
</Ginger.Run.RunSetConfig>